async_lambda/__init__.py
async_lambda/build_config.py
async_lambda/cli.py
async_lambda/config.py
async_lambda/controller.py
async_lambda/env.py
async_lambda/py.typed
async_lambda/models/__init__.py
async_lambda/models/task.py
async_lambda/models/events/__init__.py
async_lambda/models/events/api_event.py
async_lambda/models/events/base_event.py
async_lambda/models/events/managed_sqs_event.py
async_lambda/models/events/scheduled_event.py
async_lambda/models/events/unmanaged_sqs_event.py
async_lambda/models/mock/mock_context.py
async_lambda/models/mock/mock_event.py
async_lambda-0.2.1.dist-info/METADATA
async_lambda-0.2.1.dist-info/WHEEL
async_lambda-0.2.1.dist-info/entry_points.txt
async_lambda-0.2.1.dist-info/top_level.txt
async_lambda-0.2.1.dist-info/RECORD
