Metadata-Version: 2.1
Name: async-lambda
Version: 0.2.1
Summary: A framework for creating AWS Lambda Async Workflows.
Author-email: "Nuclei, Inc" <engineering@nuclei.ai>
Requires-Dist: click >=8.0.0
